BSNLibrary/__init__.py
BSNLibrary/exceptions.py
robotframework_bsnlibrary-1.1.0.data/data/Lib/site-packages/BSNLibrary/docs/index.html
robotframework_bsnlibrary-1.1.0.data/data/Lib/site-packages/BSNLibrary/license/LICENSE.txt
robotframework_bsnlibrary-1.1.0.data/data/Lib/site-packages/BSNLibrary/tests/BSNLibrary_test/1_Functional_tests.robot
robotframework_bsnlibrary-1.1.0.data/data/Lib/site-packages/BSNLibrary/tests/BSNLibrary_test/2_Error_handling.robot
robotframework_bsnlibrary-1.1.0.data/data/Lib/site-packages/BSNLibrary/tests/BSNLibrary_test/3_Demos.robot
robotframework_bsnlibrary-1.1.0.data/data/Lib/site-packages/BSNLibrary/tests/BSNLibrary_test/Resource.robot
robotframework_bsnlibrary-1.1.0.data/data/Lib/site-packages/BSNLibrary/tests/BSNLibrary_test/__init__.robot
robotframework_bsnlibrary-1.1.0.dist-info/LICENSE.txt
robotframework_bsnlibrary-1.1.0.dist-info/METADATA
robotframework_bsnlibrary-1.1.0.dist-info/WHEEL
robotframework_bsnlibrary-1.1.0.dist-info/top_level.txt
robotframework_bsnlibrary-1.1.0.dist-info/RECORD
