Metadata-Version: 2.1
Name: robotframework-bsnlibrary
Version: 1.1.0
Summary: Robot Framework library for generating BSNs (Dutch citizen service number)
Home-page: https://github.com/HaaiHenkie/bsnlibrary
Author: Henk van den Akker
Author-email: haaihenkie@users.noreply.github.com
License: MIT License (Expat)
Project-URL: Documentation, https://haaihenkie.github.io/bsnlibrary/
Project-URL: Source, https://github.com/HaaiHenkie/bsnlibrary
Project-URL: Tracker, https://github.com/HaaiHenkie/bsnlibrary/issues
Classifier: Development Status :: 5 - Production/Stable
Classifier: Intended Audience :: Developers
Classifier: Topic :: Software Development :: Testing
Classifier: Framework :: Robot Framework :: Library
Classifier: License :: OSI Approved :: MIT License
Classifier: Programming Language :: Python :: 3
Classifier: Operating System :: OS Independent
Requires-Python: >=3
License-File: LICENSE.txt
Requires-Dist: robotframework
